{
    "display": {
        "icon": {
            "id": "cobblemon:pokemon_model",
            "components": {
                "cobblemon:pokemon_item": {
                    "species": "cobblemon:nidoranf",
                    "aspects": [
                        ""
                    ]
                }
            }
        },
        "title": {
            "translate": "Nidoran Female"
        },
        "description": {
            "translate": "Have Nidoran Female in your party"
        },
        "show_toast": true,
        "announce_to_chat": true,
        "hidden": false
    },
    "parent": "cobblemon:kanto/kanto",
    "criteria": {
        "nidoranf": {
            "trigger": "cobblemon:party",
            "conditions": {
                "party": [
                    "cobblemon:nidoranf"
                ]
            }
        }
    },
    "requirements": [
        [
            "nidoranf"
        ]
    ]
}