{
    "display": {
        "icon": {
            "id": "cobblemon:pokemon_model",
            "components": {
                "cobblemon:pokemon_item": {
                    "species": "cobblemon:diancie",
                    "aspects": [
                        ""
                    ]
                }
            }
        },
        "title": {
            "translate": "Literally Pressurized Carbon"
        },
        "description": {
            "translate": "Have Diancie in your party"
        },
        "frame": "challenge",
        "show_toast": true,
        "announce_to_chat": true,
        "hidden": false
    },
    "parent": "cobblemon:legendaries/groudon",
    "criteria": {
        "diancie": {
            "trigger": "cobblemon:party",
            "conditions": {
                "party": [
                    "cobblemon:diancie"
                ]
            }
        }
    },
    "requirements": [
        [
            "diancie"
        ]
    ]
}